respan_exporter_haystack/__init__.py
respan_exporter_haystack/connector.py
respan_exporter_haystack/gateway.py
respan_exporter_haystack/logger.py
respan_exporter_haystack/tracer.py
respan_exporter_haystack-1.0.0.dist-info/LICENSE
respan_exporter_haystack-1.0.0.dist-info/METADATA
respan_exporter_haystack-1.0.0.dist-info/WHEEL
respan_exporter_haystack-1.0.0.dist-info/RECORD
