Metadata-Version: 2.1
Name: respan-exporter-haystack
Version: 1.0.0
Summary: Respan integration for Haystack pipelines with tracing and logging support
Home-page: https://respan.ai
License: MIT
Keywords: haystack,respan,llm,observability,tracing,monitoring
Author: Respan
Author-email: team@respan.ai
Requires-Python: >=3.9,<4.0
Classifier: License :: OSI Approved :: MIT License
Classifier: Programming Language :: Python :: 3
Classifier: Programming Language :: Python :: 3.9
Classifier: Programming Language :: Python :: 3.10
Classifier: Programming Language :: Python :: 3.11
Classifier: Programming Language :: Python :: 3.12
Requires-Dist: haystack-ai (>=2.0.0,<3.0.0)
Requires-Dist: requests (>=2.31.0,<3.0.0)
Project-URL: Documentation, https://docs.respan.ai
Project-URL: Repository, https://github.com/respan-ai/respan-sdks
